{
  "logs": [
    {
      "message": "Fixed server on station 0003",
      "attention": false,
      "tech": "Sam Smith",
      "date": "2020-04-17T17:53:41.608Z",
      "id": 2
    },
    {
      "id": 3,
      "message": "Hard drive restored in workstation 002",
      "attention": false,
      "tech": "Sara Wilson",
      "date": "2020-04-17T18:23:22.580Z"
    },
    {
      "message": "1122 wireless down",
      "attention": true,
      "tech": "John Doe",
      "date": "2020-04-17T17:55:35.347Z",
      "id": 4
    }
  ],
  "techs": [
    {
      "id": 1,
      "firstName": "John",
      "lastName": "Doe"
    },
    {
      "id": 2,
      "firstName": "Sam",
      "lastName": "Smith"
    },
    {
      "id": 3,
      "firstName": "Sara",
      "lastName": "Wilson"
    },
    {
      "firstName": "Jennifer",
      "lastName": "Martinez",
      "id": 4
    }
  ]
}